{
	"name": "srcemp",
	"properties": {
		"linkedServiceName": {
			"referenceName": "AzureBlobStorageSayali",
			"type": "LinkedServiceReference"
		},
		"annotations": [],
		"type": "DelimitedText",
		"typeProperties": {
			"location": {
				"type": "AzureBlobStorageLocation",
				"fileName": "Emp.txt",
				"container": "sayali"
			},
			"columnDelimiter": ",",
			"escapeChar": "\\",
			"firstRowAsHeader": true,
			"quoteChar": "\""
		},
		"schema": [
			{
				"name": "id1",
				"type": "String"
			},
			{
				"name": "name",
				"type": "String"
			},
			{
				"name": " bonus",
				"type": "String"
			}
		]
	},
	"type": "Microsoft.DataFactory/factories/datasets"
}